shdp/lib.py
shdp/py.typed
shdp/client/__init__.py
shdp/client/ws.py
shdp/client/wss.py
shdp/protocol/__init__.py
shdp/protocol/args.py
shdp/protocol/errors.py
shdp/protocol/versions.py
shdp/protocol/client/__init__.py
shdp/protocol/client/bits/__init__.py
shdp/protocol/client/bits/utils.py
shdp/protocol/client/versions/__init__.py
shdp/protocol/client/versions/v1/__init__.py
shdp/protocol/client/versions/v1/c0x0000.py
shdp/protocol/client/versions/v1/c0x0005.py
shdp/protocol/client/versions/v1/r0x0001.py
shdp/protocol/client/versions/v1/r0x0002.py
shdp/protocol/client/versions/v1/r0x0003.py
shdp/protocol/client/versions/v1/r0x0004.py
shdp/protocol/client/versions/v1/r0x0006.py
shdp/protocol/managers/__init__.py
shdp/protocol/managers/event.py
shdp/protocol/managers/ordering.py
shdp/protocol/managers/registry.py
shdp/protocol/managers/bits/__init__.py
shdp/protocol/managers/bits/decoder.py
shdp/protocol/managers/bits/encoder.py
shdp/protocol/server/__init__.py
shdp/protocol/server/bits/__init__.py
shdp/protocol/server/bits/utils.py
shdp/protocol/server/versions/__init__.py
shdp/protocol/server/versions/v1/__init__.py
shdp/protocol/server/versions/v1/c0x0001.py
shdp/protocol/server/versions/v1/c0x0002.py
shdp/protocol/server/versions/v1/c0x0003.py
shdp/protocol/server/versions/v1/c0x0004.py
shdp/protocol/server/versions/v1/c0x0006.py
shdp/protocol/server/versions/v1/r0x0000.py
shdp/protocol/server/versions/v1/r0x0005.py
shdp/server/__init__.py
shdp/server/ws.py
shdp/server/wss.py
shdp/tests/conftest.py
shdp/tests/test_0x0000.py
shdp/tests/test_0x0001.py
shdp/tests/test_0x0002.py
shdp/tests/test_0x0003.py
shdp/tests/test_0x0004.py
shdp/tests/test_0x0005.py
shdp/tests/test_0x0006.py
shdp/tests/test_client_full_front_interaction.py
shdp/tests/test_component_full_back_track.py
shdp/tests/test_interaction_full_back_track.py
shdp/tests/test_ws_client_connect.py
shdp/tests/test_ws_client_errors.py
shdp/tests/test_ws_server_errors.py
shdp/tests/test_ws_server_opening.py
shdp-1.2.4.dist-info/licenses/LICENSE.md
shdp-1.2.4.dist-info/METADATA
shdp-1.2.4.dist-info/WHEEL
shdp-1.2.4.dist-info/top_level.txt
shdp-1.2.4.dist-info/RECORD
