Metadata-Version: 2.4
Name: shdp
Version: 1.2.4
Summary: Streamline Hyperlink Dynamic Protocol
Home-page: https://github.com/StanyslasBouchon/shdp-py
Author: Devling
Author-email: contact@devling.fr
Classifier: Programming Language :: Python :: 3
Classifier: License :: OSI Approved :: MIT License
Classifier: Operating System :: OS Independent
Requires-Python: >=3.10
License-File: LICENSE.md
Requires-Dist: asyncio==4.0.0
Requires-Dist: beautifulsoup4==4.12.3
Requires-Dist: bs4==0.0.2
Requires-Dist: htmlminf==0.1.13
Requires-Dist: soupsieve==2.6
Requires-Dist: websockets==15.0.1
Dynamic: author
Dynamic: author-email
Dynamic: classifier
Dynamic: description-content-type
Dynamic: home-page
Dynamic: license-file
Dynamic: requires-dist
Dynamic: requires-python
Dynamic: summary
